{
	"format_version": "1.8.0",
	"animations": {
		"animation.wither_model.json": {
			"loop": true,
			"animation_length": 6,
			"override_previous_animation": true,
			"bones": {
				"witherHead": {
					"position": {
						"0.0": {
							"vector": [0, 0, 0]
						},
						"1.75": {
							"vector": [0, 1, 0],
							"easing": "easeInOutCubic"
						},
						"3.0": {
							"vector": [0, 0, 0]
						},
						"4.5": {
							"vector": [0, -1, 0],
							"easing": "easeInOutCubic"
						},
						"6.0": {
							"vector": [0, 0, 0],
							"easing": "easeOutExpo"
						}
					}
				}
			}
		}
	}
}